volstreet/__init__.py
volstreet/blackscholes.py
volstreet/config.py
volstreet/database_connection.py
volstreet/dealingroom.py
volstreet/decorators.py
volstreet/discord_bot.py
volstreet/exceptions.py
volstreet/parallelization.py
volstreet/performance_tracking.py
volstreet/vectorized_blackscholes.py
volstreet/volstreet_mode.json
volstreet/angel_interface/__init__.py
volstreet/angel_interface/access_rate_handler.py
volstreet/angel_interface/active_session.py
volstreet/angel_interface/async_interface.py
volstreet/angel_interface/base_websocket.py
volstreet/angel_interface/dummies.py
volstreet/angel_interface/interface.py
volstreet/angel_interface/live_feeds.py
volstreet/angel_interface/login.py
volstreet/angel_interface/order_websocket.py
volstreet/angel_interface/price_websocket.py
volstreet/angel_interface/smart_connect.py
volstreet/angel_interface/tools.py
volstreet/backtests/__init__.py
volstreet/backtests/analysis.py
volstreet/backtests/cash_backtests_polars.py
volstreet/backtests/data_updation.py
volstreet/backtests/database.py
volstreet/backtests/delta_hedging.py
volstreet/backtests/delta_optimizer.py
volstreet/backtests/framework.py
volstreet/backtests/intraday_backtest_abc.py
volstreet/backtests/proxy_functions.py
volstreet/backtests/result_processing.py
volstreet/backtests/runner.py
volstreet/backtests/tools.py
volstreet/backtests/trend.py
volstreet/backtests/underlying_info.py
volstreet/datamodule/__init__.py
volstreet/datamodule/analysis.py
volstreet/datamodule/archive.py
volstreet/datamodule/data_handling.py
volstreet/datamodule/eod_client.py
volstreet/datamodule/gambling.py
volstreet/datamodule/intraday_data.py
volstreet/datamodule/stockmock.py
volstreet/datamodule/trading_assistance.py
volstreet/deployment/__init__.py
volstreet/deployment/client.py
volstreet/deployment/client_run_template.py
volstreet/deployment/create_client.py
volstreet/deployment/create_client_linux.py
volstreet/deployment/executor.py
volstreet/deployment/websocket_template.py
volstreet-10.5.2.dist-info/METADATA
volstreet-10.5.2.dist-info/WHEEL
volstreet-10.5.2.dist-info/top_level.txt
volstreet-10.5.2.dist-info/RECORD
