Metadata-Version: 2.1
Name: volstreet
Version: 10.5.2
Summary: VolStreet is a Python library for automated trading
Home-page: https://github.com/rahulthakkr/volstreet
Author: Rahul Thakkar
Author-email: r.thakkar15@gmail.com
Classifier: Programming Language :: Python :: 3
Classifier: Operating System :: OS Independent
Requires-Dist: aiohttp<4.0,>=3.9.1
Requires-Dist: attrs<23.0,>=22.2.0
Requires-Dist: boto3<2.0,>=1.34.132
Requires-Dist: BeautifulSoup4<5.0,>=4.12.3
Requires-Dist: eod<1.0,>=0.2.1
Requires-Dist: fuzzywuzzy<1.0,>=0.18.0
Requires-Dist: joblib<2.0,>=1.3.2
Requires-Dist: logzero<2.0,>=1.7.0
Requires-Dist: numpy<2.0,>=1.26.4
Requires-Dist: pandas<3.0,>=2.0.1
Requires-Dist: polars<2.0,>=1.1.0
Requires-Dist: pulp<3.0,>=2.8.0
Requires-Dist: pyotp<3.0,>=2.8.0
Requires-Dist: python-crontab==3.2.0
Requires-Dist: python-Levenshtein<1.0,>=0.25.0
Requires-Dist: pyzmq<27.0,>=26.0.3
Requires-Dist: requests<3.0,>=2.28.2
Requires-Dist: scikit-learn==1.4.1.post1
Requires-Dist: scipy<2.0,>=1.12.0
Requires-Dist: six<2.0,>=1.16.0
Requires-Dist: smartapi-python<1.5.0,>=1.4.7
Requires-Dist: sqlalchemy<3.0,>=2.0.20
Requires-Dist: twilio<9.0,>=8.11.1
Requires-Dist: urllib3<2.0,>=1.26.14
Requires-Dist: websocket-client<2.0,>=1.5.1
